nxmx/__init__.py
nxmx/_version.py
nxmx/py.typed
nxmx-0.0.5.dist-info/licenses/LICENCE
nxmx-0.0.5.dist-info/METADATA
nxmx-0.0.5.dist-info/WHEEL
nxmx-0.0.5.dist-info/top_level.txt
nxmx-0.0.5.dist-info/RECORD
