Metadata-Version: 2.4
Name: nxmx
Version: 0.0.5
Summary: Read HDF5 data conforming to the NXmx application definition of the NeXus format
License: BSD 3-Clause License
Keywords: NeXus,NXmx
Classifier: Programming Language :: Python :: 3
Requires-Python: >=3.11
License-File: LICENCE
Requires-Dist: h5py
Requires-Dist: pint
Requires-Dist: python-dateutil
Requires-Dist: scipy
Requires-Dist: numpy
Dynamic: license-file
